{
    "design__lint_error__count": 0,
    "design__lint_timing_construct__count": 0,
    "design__lint_warning__count": 450,
    "design__inferred_latch__count": 0,
    "design__instance__count": 21749,
    "design__instance__area": 152324,
    "design__instance_unmapped__count": 0,
    "synthesis__check_error__count": 0,
    "design__max_slew_violation__count__corner:nom_tt_025C_1v80": 96,
    "design__max_fanout_violation__count__corner:nom_tt_025C_1v80": 83,
    "design__max_cap_violation__count__corner:nom_tt_025C_1v80": 52,
    "power__internal__total": 0.01523293275386095,
    "power__switching__total": 0.008347798138856888,
    "power__leakage__total": 2.356568131745007e-07,
    "power__total": 0.023580966517329216,
    "clock__skew__worst_hold__corner:nom_tt_025C_1v80": -0.48663741080884304,
    "clock__skew__worst_setup__corner:nom_tt_025C_1v80": 0.48465266505158816,
    "timing__hold__ws__corner:nom_tt_025C_1v80": 0.3266720320046221,
    "timing__setup__ws__corner:nom_tt_025C_1v80": 2.3121389901566514,
    "timing__hold__tns__corner:nom_tt_025C_1v80": 0,
    "timing__setup__tns__corner:nom_tt_025C_1v80": 0,
    "timing__hold__wns__corner:nom_tt_025C_1v80": 0,
    "timing__setup__wns__corner:nom_tt_025C_1v80": 0,
    "timing__hold_vio__count__corner:nom_tt_025C_1v80": 0,
    "timing__hold_r2r__ws__corner:nom_tt_025C_1v80": 0.326672,
    "timing__hold_r2r_vio__count__corner:nom_tt_025C_1v80": 0,
    "timing__setup_vio__count__corner:nom_tt_025C_1v80": 0,
    "timing__setup_r2r__ws__corner:nom_tt_025C_1v80": 2.312139,
    "timing__setup_r2r_vio__count__corner:nom_tt_025C_1v80": 0,
    "design__max_slew_violation__count__corner:nom_ss_100C_1v60": 783,
    "design__max_fanout_violation__count__corner:nom_ss_100C_1v60": 83,
    "design__max_cap_violation__count__corner:nom_ss_100C_1v60": 60,
    "clock__skew__worst_hold__corner:nom_ss_100C_1v60": -0.666205998113287,
    "clock__skew__worst_setup__corner:nom_ss_100C_1v60": 0.666935414661095,
    "timing__hold__ws__corner:nom_ss_100C_1v60": -0.21347213490009492,
    "timing__setup__ws__corner:nom_ss_100C_1v60": -4.074526609215584,
    "timing__hold__tns__corner:nom_ss_100C_1v60": -38.93061627704684,
    "timing__setup__tns__corner:nom_ss_100C_1v60": -1233.2805348255324,
    "timing__hold__wns__corner:nom_ss_100C_1v60": -0.21347213490009492,
    "timing__setup__wns__corner:nom_ss_100C_1v60": -4.074526609215584,
    "timing__hold_vio__count__corner:nom_ss_100C_1v60": 411,
    "timing__hold_r2r__ws__corner:nom_ss_100C_1v60": 0.905123,
    "timing__hold_r2r_vio__count__corner:nom_ss_100C_1v60": 0,
    "timing__setup_vio__count__corner:nom_ss_100C_1v60": 389,
    "timing__setup_r2r__ws__corner:nom_ss_100C_1v60": -4.074527,
    "timing__setup_r2r_vio__count__corner:nom_ss_100C_1v60": 389,
    "design__max_slew_violation__count__corner:nom_ff_n40C_1v95": 44,
    "design__max_fanout_violation__count__corner:nom_ff_n40C_1v95": 83,
    "design__max_cap_violation__count__corner:nom_ff_n40C_1v95": 52,
    "clock__skew__worst_hold__corner:nom_ff_n40C_1v95": -0.4155934325421255,
    "clock__skew__worst_setup__corner:nom_ff_n40C_1v95": 0.4123059510509316,
    "timing__hold__ws__corner:nom_ff_n40C_1v95": 0.111828216518809,
    "timing__setup__ws__corner:nom_ff_n40C_1v95": 4.935963777418485,
    "timing__hold__tns__corner:nom_ff_n40C_1v95": 0,
    "timing__setup__tns__corner:nom_ff_n40C_1v95": 0,
    "timing__hold__wns__corner:nom_ff_n40C_1v95": 0,
    "timing__setup__wns__corner:nom_ff_n40C_1v95": 0,
    "timing__hold_vio__count__corner:nom_ff_n40C_1v95": 0,
    "timing__hold_r2r__ws__corner:nom_ff_n40C_1v95": 0.111828,
    "timing__hold_r2r_vio__count__corner:nom_ff_n40C_1v95": 0,
    "timing__setup_vio__count__corner:nom_ff_n40C_1v95": 0,
    "timing__setup_r2r__ws__corner:nom_ff_n40C_1v95": 4.935964,
    "timing__setup_r2r_vio__count__corner:nom_ff_n40C_1v95": 0,
    "design__max_slew_violation__count": 973,
    "design__max_fanout_violation__count": 83,
    "design__max_cap_violation__count": 75,
    "clock__skew__worst_hold": -0.4064697304900225,
    "clock__skew__worst_setup": 0.40473939234605566,
    "timing__hold__ws": -0.3225262370688157,
    "timing__setup__ws": -4.539885040843441,
    "timing__hold__tns": -83.82947906446832,
    "timing__setup__tns": -1400.6316574109221,
    "timing__hold__wns": -0.3225262370688157,
    "timing__setup__wns": -4.539885040843441,
    "timing__hold_vio__count": 1048,
    "timing__hold_r2r__ws": 0.109013,
    "timing__hold_r2r_vio__count": 0,
    "timing__setup_vio__count": 1171,
    "timing__setup_r2r__ws": -4.539885,
    "timing__setup_r2r_vio__count": 1171,
    "design__die__bbox": "0.0 0.0 850.0 850.0",
    "design__core__bbox": "5.52 10.88 844.1 837.76",
    "design__io": 916,
    "design__die__area": 722500,
    "design__core__area": 693405,
    "design__instance__count__stdcell": 21749,
    "design__instance__area__stdcell": 152324,
    "design__instance__count__macros": 0,
    "design__instance__area__macros": 0,
    "design__instance__utilization": 0.219675,
    "design__instance__utilization__stdcell": 0.219675,
    "design__instance__count__class:inverter": 49,
    "design__instance__count__class:sequential_cell": 1580,
    "design__instance__count__class:multi_input_combinational_cell": 5917,
    "flow__warnings__count": 1,
    "flow__errors__count": 0,
    "design__instance__count__class:fill_cell": 52950,
    "design__instance__count__class:tap_cell": 9792,
    "design__power_grid_violation__count__net:VGND": 0,
    "design__power_grid_violation__count__net:VPWR": 0,
    "design__power_grid_violation__count": 0,
    "floorplan__design__io": 914,
    "design__io__hpwl": 410288876,
    "timing__drv__floating__nets": 0,
    "timing__drv__floating__pins": 0,
    "design__instance__displacement__total": 0,
    "design__instance__displacement__mean": 0,
    "design__instance__displacement__max": 0,
    "route__wirelength__estimated": 792793,
    "design__violations": 0,
    "design__instance__count__class:timing_repair_buffer": 3264,
    "design__instance__count__class:clock_buffer": 472,
    "design__instance__count__class:clock_inverter": 202,
    "design__instance__count__setup_buffer": 116,
    "design__instance__count__hold_buffer": 1095,
    "antenna__violating__nets": 35,
    "antenna__violating__pins": 36,
    "route__antenna_violation__count": 35,
    "antenna_diodes_count": 473,
    "design__instance__count__class:antenna_cell": 473,
    "route__net": 11830,
    "route__net__special": 2,
    "route__drc_errors__iter:1": 5712,
    "route__wirelength__iter:1": 867413,
    "route__drc_errors__iter:2": 2425,
    "route__wirelength__iter:2": 865586,
    "route__drc_errors__iter:3": 2076,
    "route__wirelength__iter:3": 864966,
    "route__drc_errors__iter:4": 94,
    "route__wirelength__iter:4": 864973,
    "route__drc_errors__iter:5": 5,
    "route__wirelength__iter:5": 864983,
    "route__drc_errors__iter:6": 0,
    "route__wirelength__iter:6": 865004,
    "route__drc_errors": 0,
    "route__wirelength": 865004,
    "route__vias": 85926,
    "route__vias__singlecut": 85926,
    "route__vias__multicut": 0,
    "design__disconnected_pin__count": 0,
    "design__critical_disconnected_pin__count": 0,
    "route__wirelength__max": 1723.53,
    "timing__unannotated_net__count__corner:nom_tt_025C_1v80": 310,
    "timing__unannotated_net_filtered__count__corner:nom_tt_025C_1v80": 0,
    "timing__unannotated_net__count__corner:nom_ss_100C_1v60": 310,
    "timing__unannotated_net_filtered__count__corner:nom_ss_100C_1v60": 0,
    "timing__unannotated_net__count__corner:nom_ff_n40C_1v95": 310,
    "timing__unannotated_net_filtered__count__corner:nom_ff_n40C_1v95": 0,
    "design__max_slew_violation__count__corner:min_tt_025C_1v80": 69,
    "design__max_fanout_violation__count__corner:min_tt_025C_1v80": 83,
    "design__max_cap_violation__count__corner:min_tt_025C_1v80": 35,
    "clock__skew__worst_hold__corner:min_tt_025C_1v80": -0.47735516890433977,
    "clock__skew__worst_setup__corner:min_tt_025C_1v80": 0.4765329377090481,
    "timing__hold__ws__corner:min_tt_025C_1v80": 0.3228791769783259,
    "timing__setup__ws__corner:min_tt_025C_1v80": 2.6192231347392236,
    "timing__hold__tns__corner:min_tt_025C_1v80": 0,
    "timing__setup__tns__corner:min_tt_025C_1v80": 0,
    "timing__hold__wns__corner:min_tt_025C_1v80": 0,
    "timing__setup__wns__corner:min_tt_025C_1v80": 0,
    "timing__hold_vio__count__corner:min_tt_025C_1v80": 0,
    "timing__hold_r2r__ws__corner:min_tt_025C_1v80": 0.322879,
    "timing__hold_r2r_vio__count__corner:min_tt_025C_1v80": 0,
    "timing__setup_vio__count__corner:min_tt_025C_1v80": 0,
    "timing__setup_r2r__ws__corner:min_tt_025C_1v80": 2.619223,
    "timing__setup_r2r_vio__count__corner:min_tt_025C_1v80": 0,
    "timing__unannotated_net__count__corner:min_tt_025C_1v80": 310,
    "timing__unannotated_net_filtered__count__corner:min_tt_025C_1v80": 0,
    "design__max_slew_violation__count__corner:min_ss_100C_1v60": 617,
    "design__max_fanout_violation__count__corner:min_ss_100C_1v60": 83,
    "design__max_cap_violation__count__corner:min_ss_100C_1v60": 42,
    "clock__skew__worst_hold__corner:min_ss_100C_1v60": -0.6468785690201804,
    "clock__skew__worst_setup__corner:min_ss_100C_1v60": 0.6492950805239232,
    "timing__hold__ws__corner:min_ss_100C_1v60": -0.09625545077887143,
    "timing__setup__ws__corner:min_ss_100C_1v60": -3.5262522788716004,
    "timing__hold__tns__corner:min_ss_100C_1v60": -5.7493540444704285,
    "timing__setup__tns__corner:min_ss_100C_1v60": -1048.4502878197761,
    "timing__hold__wns__corner:min_ss_100C_1v60": -0.09625545077887143,
    "timing__setup__wns__corner:min_ss_100C_1v60": -3.5262522788716004,
    "timing__hold_vio__count__corner:min_ss_100C_1v60": 160,
    "timing__hold_r2r__ws__corner:min_ss_100C_1v60": 0.899775,
    "timing__hold_r2r_vio__count__corner:min_ss_100C_1v60": 0,
    "timing__setup_vio__count__corner:min_ss_100C_1v60": 386,
    "timing__setup_r2r__ws__corner:min_ss_100C_1v60": -3.526252,
    "timing__setup_r2r_vio__count__corner:min_ss_100C_1v60": 386,
    "timing__unannotated_net__count__corner:min_ss_100C_1v60": 310,
    "timing__unannotated_net_filtered__count__corner:min_ss_100C_1v60": 0,
    "design__max_slew_violation__count__corner:min_ff_n40C_1v95": 39,
    "design__max_fanout_violation__count__corner:min_ff_n40C_1v95": 83,
    "design__max_cap_violation__count__corner:min_ff_n40C_1v95": 35,
    "clock__skew__worst_hold__corner:min_ff_n40C_1v95": -0.4064697304900225,
    "clock__skew__worst_setup__corner:min_ff_n40C_1v95": 0.40473939234605566,
    "timing__hold__ws__corner:min_ff_n40C_1v95": 0.10901302391564792,
    "timing__setup__ws__corner:min_ff_n40C_1v95": 5.13640122750702,
    "timing__hold__tns__corner:min_ff_n40C_1v95": 0,
    "timing__setup__tns__corner:min_ff_n40C_1v95": 0,
    "timing__hold__wns__corner:min_ff_n40C_1v95": 0,
    "timing__setup__wns__corner:min_ff_n40C_1v95": 0,
    "timing__hold_vio__count__corner:min_ff_n40C_1v95": 0,
    "timing__hold_r2r__ws__corner:min_ff_n40C_1v95": 0.109013,
    "timing__hold_r2r_vio__count__corner:min_ff_n40C_1v95": 0,
    "timing__setup_vio__count__corner:min_ff_n40C_1v95": 0,
    "timing__setup_r2r__ws__corner:min_ff_n40C_1v95": 5.159976,
    "timing__setup_r2r_vio__count__corner:min_ff_n40C_1v95": 0,
    "timing__unannotated_net__count__corner:min_ff_n40C_1v95": 310,
    "timing__unannotated_net_filtered__count__corner:min_ff_n40C_1v95": 0,
    "design__max_slew_violation__count__corner:max_tt_025C_1v80": 119,
    "design__max_fanout_violation__count__corner:max_tt_025C_1v80": 83,
    "design__max_cap_violation__count__corner:max_tt_025C_1v80": 68,
    "clock__skew__worst_hold__corner:max_tt_025C_1v80": -0.5010488832321791,
    "clock__skew__worst_setup__corner:max_tt_025C_1v80": 0.4967566498752831,
    "timing__hold__ws__corner:max_tt_025C_1v80": 0.3296198962629781,
    "timing__setup__ws__corner:max_tt_025C_1v80": 2.0209736678405794,
    "timing__hold__tns__corner:max_tt_025C_1v80": 0,
    "timing__setup__tns__corner:max_tt_025C_1v80": 0,
    "timing__hold__wns__corner:max_tt_025C_1v80": 0,
    "timing__setup__wns__corner:max_tt_025C_1v80": 0,
    "timing__hold_vio__count__corner:max_tt_025C_1v80": 0,
    "timing__hold_r2r__ws__corner:max_tt_025C_1v80": 0.32962,
    "timing__hold_r2r_vio__count__corner:max_tt_025C_1v80": 0,
    "timing__setup_vio__count__corner:max_tt_025C_1v80": 0,
    "timing__setup_r2r__ws__corner:max_tt_025C_1v80": 2.020974,
    "timing__setup_r2r_vio__count__corner:max_tt_025C_1v80": 0,
    "timing__unannotated_net__count__corner:max_tt_025C_1v80": 310,
    "timing__unannotated_net_filtered__count__corner:max_tt_025C_1v80": 0,
    "design__max_slew_violation__count__corner:max_ss_100C_1v60": 973,
    "design__max_fanout_violation__count__corner:max_ss_100C_1v60": 83,
    "design__max_cap_violation__count__corner:max_ss_100C_1v60": 75,
    "clock__skew__worst_hold__corner:max_ss_100C_1v60": -0.686564602380829,
    "clock__skew__worst_setup__corner:max_ss_100C_1v60": 0.684872844488059,
    "timing__hold__ws__corner:max_ss_100C_1v60": -0.3225262370688157,
    "timing__setup__ws__corner:max_ss_100C_1v60": -4.539885040843441,
    "timing__hold__tns__corner:max_ss_100C_1v60": -83.82947906446832,
    "timing__setup__tns__corner:max_ss_100C_1v60": -1400.6316574109221,
    "timing__hold__wns__corner:max_ss_100C_1v60": -0.3225262370688157,
    "timing__setup__wns__corner:max_ss_100C_1v60": -4.539885040843441,
    "timing__hold_vio__count__corner:max_ss_100C_1v60": 477,
    "timing__hold_r2r__ws__corner:max_ss_100C_1v60": 0.913406,
    "timing__hold_r2r_vio__count__corner:max_ss_100C_1v60": 0,
    "timing__setup_vio__count__corner:max_ss_100C_1v60": 396,
    "timing__setup_r2r__ws__corner:max_ss_100C_1v60": -4.539885,
    "timing__setup_r2r_vio__count__corner:max_ss_100C_1v60": 396,
    "timing__unannotated_net__count__corner:max_ss_100C_1v60": 310,
    "timing__unannotated_net_filtered__count__corner:max_ss_100C_1v60": 0,
    "design__max_slew_violation__count__corner:max_ff_n40C_1v95": 49,
    "design__max_fanout_violation__count__corner:max_ff_n40C_1v95": 83,
    "design__max_cap_violation__count__corner:max_ff_n40C_1v95": 67,
    "clock__skew__worst_hold__corner:max_ff_n40C_1v95": -0.42739477056074815,
    "clock__skew__worst_setup__corner:max_ff_n40C_1v95": 0.42403934341852556,
    "timing__hold__ws__corner:max_ff_n40C_1v95": 0.11396917066004648,
    "timing__setup__ws__corner:max_ff_n40C_1v95": 4.709484491238619,
    "timing__hold__tns__corner:max_ff_n40C_1v95": 0,
    "timing__setup__tns__corner:max_ff_n40C_1v95": 0,
    "timing__hold__wns__corner:max_ff_n40C_1v95": 0,
    "timing__setup__wns__corner:max_ff_n40C_1v95": 0,
    "timing__hold_vio__count__corner:max_ff_n40C_1v95": 0,
    "timing__hold_r2r__ws__corner:max_ff_n40C_1v95": 0.113969,
    "timing__hold_r2r_vio__count__corner:max_ff_n40C_1v95": 0,
    "timing__setup_vio__count__corner:max_ff_n40C_1v95": 0,
    "timing__setup_r2r__ws__corner:max_ff_n40C_1v95": 4.709485,
    "timing__setup_r2r_vio__count__corner:max_ff_n40C_1v95": 0,
    "timing__unannotated_net__count__corner:max_ff_n40C_1v95": 310,
    "timing__unannotated_net_filtered__count__corner:max_ff_n40C_1v95": 0,
    "timing__unannotated_net__count": 310,
    "timing__unannotated_net_filtered__count": 0,
    "design_powergrid__voltage__worst__net:VPWR__corner:nom_tt_025C_1v80": 1.7994,
    "design_powergrid__drop__average__net:VPWR__corner:nom_tt_025C_1v80": 1.79994,
    "design_powergrid__drop__worst__net:VPWR__corner:nom_tt_025C_1v80": 0.000595891,
    "design_powergrid__voltage__worst__net:VGND__corner:nom_tt_025C_1v80": 0.000724204,
    "design_powergrid__drop__average__net:VGND__corner:nom_tt_025C_1v80": 6.33576e-05,
    "design_powergrid__drop__worst__net:VGND__corner:nom_tt_025C_1v80": 0.000724204,
    "design_powergrid__voltage__worst": 0.000724204,
    "design_powergrid__voltage__worst__net:VPWR": 1.7994,
    "design_powergrid__drop__worst": 0.000724204,
    "design_powergrid__drop__worst__net:VPWR": 0.000595891,
    "design_powergrid__voltage__worst__net:VGND": 0.000724204,
    "design_powergrid__drop__worst__net:VGND": 0.000724204,
    "ir__voltage__worst": 1.8,
    "ir__drop__avg": 6.36e-05,
    "ir__drop__worst": 0.000596,
    "design__xor_difference__count": 0,
    "magic__drc_error__count": 0,
    "klayout__drc_error__count": 0,
    "magic__illegal_overlap__count": 0,
    "design__lvs_device_difference__count": 0,
    "design__lvs_net_difference__count": 0,
    "design__lvs_property_fail__count": 0,
    "design__lvs_error__count": 0,
    "design__lvs_unmatched_device__count": 0,
    "design__lvs_unmatched_net__count": 0,
    "design__lvs_unmatched_pin__count": 0
}